DockerSwarmYuanmaFenxi/README.md
DockerSwarmYuanmaFenxi/__init__.py
DockerSwarmYuanmaFenxi/__main__.py
DockerSwarmYuanmaFenxi/file.epub
DockerSwarmYuanmaFenxi/index.html
DockerSwarmYuanmaFenxi/css/__init__.py
DockerSwarmYuanmaFenxi/css/annotations.css
DockerSwarmYuanmaFenxi/css/main.css
DockerSwarmYuanmaFenxi/css/normalize.css
DockerSwarmYuanmaFenxi/css/popup.css
DockerSwarmYuanmaFenxi/font/__init__.py
DockerSwarmYuanmaFenxi/font/fontello.eot
DockerSwarmYuanmaFenxi/font/fontello.svg
DockerSwarmYuanmaFenxi/font/fontello.ttf
DockerSwarmYuanmaFenxi/font/fontello.woff
DockerSwarmYuanmaFenxi/img/__init__.py
DockerSwarmYuanmaFenxi/img/annotator-glyph-sprite.png
DockerSwarmYuanmaFenxi/img/annotator-icon-sprite.png
DockerSwarmYuanmaFenxi/img/apple-touch-icon.png
DockerSwarmYuanmaFenxi/img/cancelfullscreen.png
DockerSwarmYuanmaFenxi/img/close.png
DockerSwarmYuanmaFenxi/img/fullscreen.png
DockerSwarmYuanmaFenxi/img/loader.gif
DockerSwarmYuanmaFenxi/img/menu-icon.png
DockerSwarmYuanmaFenxi/img/save.png
DockerSwarmYuanmaFenxi/img/saved.png
DockerSwarmYuanmaFenxi/img/settings-s.png
DockerSwarmYuanmaFenxi/img/settings.png
DockerSwarmYuanmaFenxi/img/star.png
DockerSwarmYuanmaFenxi/js/__init__.py
DockerSwarmYuanmaFenxi/js/epub.js
DockerSwarmYuanmaFenxi/js/epub.min.js
DockerSwarmYuanmaFenxi/js/epub.min.map
DockerSwarmYuanmaFenxi/js/hooks.min.js
DockerSwarmYuanmaFenxi/js/hooks.min.map
DockerSwarmYuanmaFenxi/js/reader.js
DockerSwarmYuanmaFenxi/js/reader.js.map
DockerSwarmYuanmaFenxi/js/reader.min.js
DockerSwarmYuanmaFenxi/js/reader.min.map
DockerSwarmYuanmaFenxi/js/hooks/__init__.py
DockerSwarmYuanmaFenxi/js/hooks/extensions/__init__.py
DockerSwarmYuanmaFenxi/js/hooks/extensions/highlight.js
DockerSwarmYuanmaFenxi/js/libs/__init__.py
DockerSwarmYuanmaFenxi/js/libs/jquery.min.js
DockerSwarmYuanmaFenxi/js/libs/localforage.min.js
DockerSwarmYuanmaFenxi/js/libs/screenfull.js
DockerSwarmYuanmaFenxi/js/libs/screenfull.min.js
DockerSwarmYuanmaFenxi/js/libs/zip.min.js
docker_swarm_yuanma_fenxi-2024.3.3.0.dist-info/METADATA
docker_swarm_yuanma_fenxi-2024.3.3.0.dist-info/WHEEL
docker_swarm_yuanma_fenxi-2024.3.3.0.dist-info/entry_points.txt
docker_swarm_yuanma_fenxi-2024.3.3.0.dist-info/top_level.txt
docker_swarm_yuanma_fenxi-2024.3.3.0.dist-info/RECORD
